{"name":"docker","slug":"docker","count":1,"postlist":[{"title":"如何使用Docker部署一个go程序","uid":"6d1c99c12c344c631fb3ed115b7df580","slug":"docker-go","date":"2023-03-12T07:30:59.000Z","updated":"2023-03-12T08:40:47.787Z","comments":true,"path":"api/articles/docker-go.json","keywords":null,"cover":"https://cdn.pixabay.com/photo/2013/04/04/12/34/mountains-100367_960_720.jpg","text":"Docker定义Docker 是一个开源的应用容器引擎，让开发者可以打包他们的应用以及依赖包到一个可移植的镜像中，然后发布到任何流行的 Linux或Windows操作系统的机器上，也可以实现虚拟化。容器是完全使用沙箱机制，相互之间不会有任何接口。 本文我们介绍怎么使用 Docke...","link":"","photos":[],"count_time":{"symbolsCount":"1k","symbolsTime":"1 mins."},"categories":[],"tags":[{"name":"docker","slug":"docker","count":1,"path":"api/tags/docker.json"},{"name":"golang","slug":"golang","count":2,"path":"api/tags/golang.json"}],"author":{"name":"Sh1mwww","slug":"blog-author","avatar":"https://img.onl/qZjVAP","link":"/","description":"及时行乐","socials":{"github":"","twitter":"","stackoverflow":"","wechat":"","qq":"","weibo":"","zhihu":"","csdn":"","juejin":"","customs":{}}}}]}